{
  "generated_at": "2026-06-02 22:45:24",
  "macro": {
    "S&P500": {
      "price": 7592.25,
      "change": -0.1
    },
    "NASDAQ": {
      "price": 27004.9,
      "change": -0.3
    },
    "DOW": {
      "price": 51179.59,
      "change": 0.2
    },
    "VIX": {
      "price": 16.18,
      "change": 0.81
    },
    "필라델피아반도체": {
      "price": 13430.58,
      "change": 3.59
    },
    "러셀2000": {
      "price": 2901.36,
      "change": -0.15
    },
    "영국FTSE": {
      "price": 10342.06,
      "change": 0.03
    },
    "독일DAX": {
      "price": 25123.0,
      "change": 0.48
    },
    "니케이": {
      "price": 66734.24,
      "change": -0.3
    },
    "항셍": {
      "price": 26038.32,
      "change": 2.52
    },
    "달러인덱스": {
      "price": 99.1,
      "change": -0.1
    },
    "국채10Y": {
      "price": 4.44,
      "change": -0.76
    },
    "국채30Y": {
      "price": 4.95,
      "change": -0.74
    },
    "코스피": {
      "price": 8801.49,
      "change": 0.15
    },
    "코스닥": {
      "price": 1026.03,
      "change": -2.29
    },
    "금": {
      "price": 4538.0,
      "change": 1.4
    },
    "WTI유가": {
      "price": 92.32,
      "change": 0.17
    },
    "원달러": {
      "price": 1515.61,
      "change": 0.58
    },
    "구리": {
      "price": 6.67,
      "change": 2.22
    }
  }
}