{
  "generated_at": "2026-06-08 22:30:13",
  "macro": {
    "S&P500": {
      "price": 7444.06,
      "change": 0.82
    },
    "NASDAQ": {
      "price": 25709.43,
      "change": -4.18
    },
    "DOW": {
      "price": 51032.21,
      "change": 0.33
    },
    "VIX": {
      "price": 18.7,
      "change": -13.06
    },
    "필라델피아반도체": {
      "price": 12220.76,
      "change": -10.26
    },
    "러셀2000": {
      "price": 2833.5,
      "change": -3.47
    },
    "영국FTSE": {
      "price": 10354.4,
      "change": -0.13
    },
    "독일DAX": {
      "price": 24646.1,
      "change": -0.46
    },
    "니케이": {
      "price": 64024.6,
      "change": -3.85
    },
    "항셍": {
      "price": 24657.06,
      "change": -1.22
    },
    "달러인덱스": {
      "price": 99.88,
      "change": -0.19
    },
    "국채10Y": {
      "price": 4.53,
      "change": -0.18
    },
    "국채30Y": {
      "price": 5.0,
      "change": 0.1
    },
    "코스피": {
      "price": 7484.41,
      "change": -8.29
    },
    "코스닥": {
      "price": 911.39,
      "change": -9.08
    },
    "금": {
      "price": 4351.0,
      "change": 0.32
    },
    "WTI유가": {
      "price": 91.83,
      "change": 1.42
    },
    "원달러": {
      "price": 1525.53,
      "change": -0.49
    },
    "구리": {
      "price": 6.37,
      "change": 1.74
    }
  }
}